Workbook

Sheet Summary
A1: IKEJA CITY MALL - FIRE DETECTION & ALARM SYSTEM OVERHAUL
A2: Bid comparison summary - 5 quotations against the client's RFP. All figures NGN.
A3: Displayed to the nearest naira; underlying values are exact to the kobo. Blue = source figure, black = formula.
B5: TotaGO | C5: Emo-Technical | D5: Potreal (PISL) | E5: JML / Fadayomi | F5: Roundbox
A6: Source document | B6: ikeja city mall Fire Alarm Deployment.pdf | C6: Bill for ikeja mall fire system.pdf | D6: ICM ADDRESSABLE FIRE ALARM UPGRADE.pdf | E6: ICM SYSTEM REVAMP PROPOSAL(3).PDF | F6: IKEJA CITY MALL FIRE ALARM SYSTEM.pdf
A7: Quote date | B7: =Compliance!B18 -> 46101 | C7: =Compliance!C18 -> 46220 | D7: =Compliance!D18 -> 46195 | E7: =Compliance!E18 -> 46196 | F7: =Compliance!F18 -> 46234
A8: Equipment offered | B8: GENT | C8: GENT | D8: GENT | E8: GENT | F8: TANDA (substituted)
A9: Subtotal ex VAT, as quoted | B9: ='Bid Tab'!E20 -> 86825000 | C9: ='Bid Tab'!F20 -> 78201500 | D9: ='Bid Tab'!G20 -> 73490000 | E9: ='Bid Tab'!H20 -> 68050000 | F9: ='Bid Tab'!I20 -> 34167433
A10: VAT | B10: ='Bid Tab'!E22 -> 6511875 | C10: ='Bid Tab'!F22 -> 5865112.5 | D10: ='Bid Tab'!G22 -> 5511750 | E10: ='Bid Tab'!H22 -> 5103750 | F10: ='Bid Tab'!I22 -> 2562557.5
A11: TOTAL AS QUOTED | B11: ='Bid Tab'!E23 -> 93336875 | C11: ='Bid Tab'!F23 -> 84066612 | D11: ='Bid Tab'!G23 -> 79001750 | E11: ='Bid Tab'!H23 -> 73153750 | F11: ='Bid Tab'!I23 -> 36729991
A12: Normalisation adjustments | B12: =Normalisation!C7+Normalisation!C8 -> -300000 | C12: =Normalisation!D7+Normalisation!D8 -> 0 | D12: =Normalisation!E7+Normalisation!E8 -> 0 | E12: =Normalisation!F7+Normalisation!F8 -> 3450000 | F12: =Normalisation!G7+Normalisation!G8 -> 903299.67
A13: ADJUSTED TOTAL (like-for-like, incl. VAT) | B13: =Normalisation!C11 -> 93014375 | C13: =Normalisation!D11 -> 84066612 | D13: =Normalisation!E11 -> 79001750 | E13: =Normalisation!F11 -> 76862500 | F13: =Normalisation!G11 -> 37701038
A14: Rank (compliant bids only) | B14: =RANK(B13,$B$13:$E$13,1) -> 4 | C14: =RANK(C13,$B$13:$E$13,1) -> 3 | D14: =RANK(D13,$B$13:$E$13,1) -> 2 | E14: =RANK(E13,$B$13:$E$13,1) -> 1 | F14: n/a
A15: Premium vs lowest compliant bid | B15: =B13/MIN($B$13:$E$13)-1 -> 0.21013986 | C15: =C13/MIN($B$13:$E$13)-1 -> 0.093727273 | D15: =D13/MIN($B$13:$E$13)-1 -> 0.027832168 | E15: =E13/MIN($B$13:$E$13)-1 -> 0 | F15: =F13/MIN($B$13:$E$13)-1 -> -0.50950024
A16: Quote still valid at 31-Jul-2026 | B16: =Compliance!B21 -> EXPIRED | C16: =Compliance!C21 -> Valid | D16: =Compliance!D21 -> EXPIRED | E16: =Compliance!E21 -> EXPIRED | F16: =Compliance!F21 -> Valid
A17: Assessment | B17: Compliant but most expensive, arithmetically unsound, and long expired. | C17: Compliant, arithmetically clean, and the only bid answering every commercial question the RFP asked. | D17: Compliant and mid-priced; commercial terms absent from the quotation. | E17: Cheapest compliant bid, but one panel short and terms absent. | F17: NON-COMPLIANT on equipment - price is not comparable.
A19: How to read this workbook
A20: Bid Tab - every bid mapped onto the client's 13-line bill of quantities, with the median, low and high of the four GENT bids per line.
A21: Unit Rates - effective rate per unit, derived from the line totals, so a bidder's printed rate and what it actually charged can diverge visibly.
A22: Normalisation - the bridge from as-quoted to like-for-like: arithmetic corrections and imputed unpriced scope, each shown separately.
A23: Compliance - the RFP's contractor responsibilities and required commercial submission, tested bid by bid, plus validity and document-integrity flags.
A24: Notes & Sources - every assumption, every imputed number, and the source document behind each column.

Sheet Bid Tab
A1: IKEJA CITY MALL - ADDRESSABLE FIRE DETECTION & ALARM SYSTEM
A2: Normalised bid tabulation - all bids mapped line-by-line onto the client's RFP bill of quantities
A3: All figures in Nigerian Naira (NGN), exclusive of VAT unless stated. Blue = figure taken from a bidder's document; black = formula. Blank = item not quoted.
A5: RFP Item | B5: Description (per client RFP) | C5: Qty | D5: Unit | E5: TotaGO | F5: Emo-Technical | G5: Potreal (PISL) | H5: JML / Fadayomi | I5: Roundbox | J5: Median (GENT bids) | K5: Lowest (GENT bids) | L5: Highest (GENT bids) | M5: Notes / exceptions
A6: 1 | B6: GENT Vigilon Plus 24 addressable fire alarm main panel, 1-4 loop, integrated with existing system | C6: 1 | D6: No. | E6: 7000000 | F6: 5100000 | G6: 5500000 | H6: 3200000 | I6: 3006479.8 | J6: =MEDIAN(E6:H6) -> 5300000 | K6: =MIN(E6:H6) -> 3200000 | L6: =MAX(E6:H6) -> 7000000 | M6: Roundbox quotes TWO panels (TX7008-6 6-loop main + TX7004 sub-panel) against this single line - scope clarification required.
A7: 2 | B7: GENT S4 addressable smoke detectors c/w detector bases | C7: 385 | D7: No. | E7: 27335000 | F7: 29260000 | G7: 21945000 | H7: 28875000 | I7: 7946066.6 | J7: =MEDIAN(E7:H7) -> 28105000 | K7: =MIN(E7:H7) -> 21945000 | L7: =MAX(E7:H7) -> 29260000 | M7: Roundbox figure = TX7100 detector 7,118,572.31 + TX7980 bases 827,494.25.
A8: 3 | B8: GENT S4 "VAD" addressable heat detectors | C8: 60 | D8: No. | E8: 4260000 | F8: 4416000 | G8: 3420000 | H8: 4500000 | I8: 1182134.6 | J8: =MEDIAN(E8:H8) -> 4338000 | K8: =MIN(E8:H8) -> 3420000 | L8: =MAX(E8:H8) -> 4500000 | M8: Gent does make heat sensors with an integrated VAD strobe (S4-720-V-VAD-HPR / -HPW), so the RFP wording describes a real product. But at 57,000-76,000 these lines are priced like PLAIN heat sensors - below the sounder-VAD lines at 90,000-145,000. Confirm which variant is being supplied before award.
A9: 4 | B9: GENT S4-34842 addressable manual call points (MCPs) | C9: 35 | D9: No. | E9: 3430000 | F9: 4581500 | G9: 3325000 | H9: 3675000 | I9: 917187.68 | J9: =MEDIAN(E9:H9) -> 3552500 | K9: =MIN(E9:H9) -> 3325000 | L9: =MAX(E9:H9) -> 4581500 | M9: Roundbox figure = TX7140 call point 788,916.43 + TX7140-MB boxes 128,271.25.
A10: 5 | B10: GENT S4 addressable sounders | C10: 60 | D10: No. | E10: 5700000 | F10: 7194000 | G10: 5400000 | H10: 8700000 | I10: 1625228.5 | J10: =MEDIAN(E10:H10) -> 6447000 | K10: =MIN(E10:H10) -> 5400000 | L10: =MAX(E10:H10) -> 8700000
A11: 6 | B11: GENT two-channel interface modules | C11: 20 | D11: No. | E11: 8000000 | F11: 2690000 | G11: 6000000 | H11: 3300000 | I11: 902721 | J11: =MEDIAN(E11:H11) -> 4650000 | K11: =MIN(E11:H11) -> 2690000 | L11: =MAX(E11:H11) -> 8000000
A12: 7 | B12: 1.5mm2 two-core flexible copper shielded fire-resistant cable, incl. termination and testing | C12: 30 | D12: drum (100m) | E12: 6300000 | F12: 4440000 | G12: 4500000 | H12: 6150000 | I12: 6600000 | J12: =MEDIAN(E12:H12) -> 5325000 | K12: =MIN(E12:H12) -> 4440000 | L12: =MAX(E12:H12) -> 6300000
A13: 8 | B13: Piping, trunking, containment systems, supports and accessories for cable routing | C13: 1 | D13: Lot | E13: 1000000 | F13: 5150000 | G13: 600000 | H13: 500000 | I13: 1000000 | J13: =MEDIAN(E13:H13) -> 800000 | K13: =MIN(E13:H13) -> 500000 | L13: =MAX(E13:H13) -> 5150000
A14: 9 | B14: GENT Plus addressable loop cards | C14: 4 | D14: No. | E14: 1500000 | F14: 1800000 | G14: 1800000 | H14: 1540000 | I14: 301099.89 | J14: =MEDIAN(E14:H14) -> 1670000 | K14: =MIN(E14:H14) -> 1500000 | L14: =MAX(E14:H14) -> 1800000 | M14: TotaGO prints 4 No. @ 300,000 = 1,500,000; 4 x 300,000 = 1,200,000. Over-stated by 300,000 - corrected on 'Normalisation'. Roundbox supplies 1 card only, not 4.
A15: 10 | B15: GENT 1-2 loop fire alarm panel (system expansion / integration) | C15: 1 | D15: No. | E15: 3000000 | F15: 3450000 | G15: 3500000 | I15: 879271.19 | J15: =MEDIAN(E15:H15) -> 3450000 | K15: =MIN(E15:H15) -> 3000000 | L15: =MAX(E15:H15) -> 3500000 | M15: JML/Fadayomi does not quote this item at all. Imputed on 'Normalisation'.
A16: 11 | B16: GENT network card for inter-panel communication and networking | C16: 1 | D16: No. | E16: 800000 | F16: 620000 | G16: 1000000 | H16: 110000 | I16: 104683.67 | J16: =MEDIAN(E16:H16) -> 710000 | K16: =MIN(E16:H16) -> 110000 | L16: =MAX(E16:H16) -> 1000000
A17: 12 | B17: Associated civil works, builders' works, installation materials and ancillary accessories | C17: 1 | D17: Lot | E17: 3500000 | F17: 5300000 | G17: 4000000 | H17: 500000 | I17: 1000000 | J17: =MEDIAN(E17:H17) -> 3750000 | K17: =MIN(E17:H17) -> 500000 | L17: =MAX(E17:H17) -> 5300000
A18: 13 | B18: Professional services: design review, programming, testing, commissioning, as-built documentation, training, labour, handover | C18: 1 | D18: Lot | E18: 15000000 | F18: 4200000 | G18: 12500000 | H18: 7000000 | I18: 8577100 | J18: =MEDIAN(E18:H18) -> 9750000 | K18: =MIN(E18:H18) -> 4200000 | L18: =MAX(E18:H18) -> 15000000 | M18: Roundbox figure = professional services 1,500,000 + separately stated installation cost 7,077,100.03, combined for comparability.
A19: - | B19: Items priced outside the RFP bill of quantities (detail below) | D19: Lot | I19: 125460.58 | M19: Included here because it forms part of the subtotal the bidder printed. Excluded from the median / low / high, which cover RFP scope only.
B20: SUBTOTAL (ex VAT), as quoted | E20: =SUM(E6:E19) -> 86825000 | F20: =SUM(F6:F19) -> 78201500 | G20: =SUM(G6:G19) -> 73490000 | H20: =SUM(H6:H19) -> 68050000 | I20: =SUM(I6:I19) -> 34167433 | M20: Reconciles exactly to the subtotal printed on each bidder's own quotation.
B21: VAT rate applied (Nigeria standard rate) | E21: 0.075 | M21: Key input. All five bids compute VAT at this rate; Roundbox mislabels it "5%" but its arithmetic is 7.5%.
B22: VAT | E22: =E20*$E$21 -> 6511875 | F22: =F20*$E$21 -> 5865112.5 | G22: =G20*$E$21 -> 5511750 | H22: =H20*$E$21 -> 5103750 | I22: =I20*$E$21 -> 2562557.5
B23: TOTAL AS QUOTED (incl. VAT) | E23: =E20+E22 -> 93336875 | F23: =F20+F22 -> 84066612 | G23: =G20+G22 -> 79001750 | H23: =H20+H22 -> 73153750 | I23: =I20+I22 -> 36729991
B25: Reconciliation to each bidder's printed subtotal
B26: Subtotal as printed on the bidder's document | E26: 86825000 | F26: 78201500 | G26: 73490000 | H26: 68050000 | I26: 34167433
B27: Difference vs this tabulation | E27: =E20-E26 -> 0 | F27: =F20-F26 -> 0 | G27: =G20-G26 -> 0 | H27: =H20-H26 -> 0 | I27: =I20-I26 -> 0 | M27: Zero across the row confirms every line was transcribed and mapped without loss.
B28: Detail: items priced outside the RFP bill of quantities
B29: Bidder | C29: Item | E29: Amount
B30: Roundbox | C30: TANDA TX7932 handheld programmer | E30: 125460.58
B32: Not deducted from the adjusted totals: whether this scope is wanted is the client's call, and guessing would move the comparison on judgement rather than evidence. Roundbox also prices two panels against the single main-panel line - see the note on item 1.

Sheet Unit Rates
A1: UNIT RATE COMPARISON
A2: Effective unit rate = quoted line total / RFP quantity. Derived by formula from 'Bid Tab', so it reflects what each bidder actually billed per unit.
A3: Roundbox rates are for TANDA equipment, not GENT - shown for reference only, they are not a like-for-like price.
A5: RFP Item | B5: Description | C5: Qty | E5: TotaGO | F5: Emo-Technical | G5: Potreal (PISL) | H5: JML / Fadayomi | I5: Roundbox | J5: Median rate (GENT bids) | K5: Spread (high / low) | L5: Comment
A6: 1 | B6: GENT Vigilon Plus 24 addressable fire alarm main panel, 1-4 loop, integrated with existing system | C6: ='Bid Tab'!C6 -> 1 | E6: =IF('Bid Tab'!E6="","",IFERROR('Bid Tab'!E6/'Bid Tab'!$C$6,"")) -> 7000000 | F6: =IF('Bid Tab'!F6="","",IFERROR('Bid Tab'!F6/'Bid Tab'!$C$6,"")) -> 5100000 | G6: =IF('Bid Tab'!G6="","",IFERROR('Bid Tab'!G6/'Bid Tab'!$C$6,"")) -> 5500000 | H6: =IF('Bid Tab'!H6="","",IFERROR('Bid Tab'!H6/'Bid Tab'!$C$6,"")) -> 3200000 | I6: =IF('Bid Tab'!I6="","",IFERROR('Bid Tab'!I6/'Bid Tab'!$C$6,"")) -> 3006479.8 | J6: =MEDIAN(E6:H6) -> 5300000 | K6: =IFERROR(MAX(E6:H6)/MIN(E6:H6),"") -> 2.1875
A7: 2 | B7: GENT S4 addressable smoke detectors c/w detector bases | C7: ='Bid Tab'!C7 -> 385 | E7: =IF('Bid Tab'!E7="","",IFERROR('Bid Tab'!E7/'Bid Tab'!$C$7,"")) -> 71000 | F7: =IF('Bid Tab'!F7="","",IFERROR('Bid Tab'!F7/'Bid Tab'!$C$7,"")) -> 76000 | G7: =IF('Bid Tab'!G7="","",IFERROR('Bid Tab'!G7/'Bid Tab'!$C$7,"")) -> 57000 | H7: =IF('Bid Tab'!H7="","",IFERROR('Bid Tab'!H7/'Bid Tab'!$C$7,"")) -> 75000 | I7: =IF('Bid Tab'!I7="","",IFERROR('Bid Tab'!I7/'Bid Tab'!$C$7,"")) -> 20639.134 | J7: =MEDIAN(E7:H7) -> 73000 | K7: =IFERROR(MAX(E7:H7)/MIN(E7:H7),"") -> 1.3333333 | L7: Widest hardware spread in the tab: PISL 57,000 vs Emo 76,000 per smoke detector on 385 units = 7.3m swing.
A8: 3 | B8: GENT S4 "VAD" addressable heat detectors | C8: ='Bid Tab'!C8 -> 60 | E8: =IF('Bid Tab'!E8="","",IFERROR('Bid Tab'!E8/'Bid Tab'!$C$8,"")) -> 71000 | F8: =IF('Bid Tab'!F8="","",IFERROR('Bid Tab'!F8/'Bid Tab'!$C$8,"")) -> 73600 | G8: =IF('Bid Tab'!G8="","",IFERROR('Bid Tab'!G8/'Bid Tab'!$C$8,"")) -> 57000 | H8: =IF('Bid Tab'!H8="","",IFERROR('Bid Tab'!H8/'Bid Tab'!$C$8,"")) -> 75000 | I8: =IF('Bid Tab'!I8="","",IFERROR('Bid Tab'!I8/'Bid Tab'!$C$8,"")) -> 19702.244 | J8: =MEDIAN(E8:H8) -> 72300 | K8: =IFERROR(MAX(E8:H8)/MIN(E8:H8),"") -> 1.3157895
A9: 4 | B9: GENT S4-34842 addressable manual call points (MCPs) | C9: ='Bid Tab'!C9 -> 35 | E9: =IF('Bid Tab'!E9="","",IFERROR('Bid Tab'!E9/'Bid Tab'!$C$9,"")) -> 98000 | F9: =IF('Bid Tab'!F9="","",IFERROR('Bid Tab'!F9/'Bid Tab'!$C$9,"")) -> 130900 | G9: =IF('Bid Tab'!G9="","",IFERROR('Bid Tab'!G9/'Bid Tab'!$C$9,"")) -> 95000 | H9: =IF('Bid Tab'!H9="","",IFERROR('Bid Tab'!H9/'Bid Tab'!$C$9,"")) -> 105000 | I9: =IF('Bid Tab'!I9="","",IFERROR('Bid Tab'!I9/'Bid Tab'!$C$9,"")) -> 26205.362 | J9: =MEDIAN(E9:H9) -> 101500 | K9: =IFERROR(MAX(E9:H9)/MIN(E9:H9),"") -> 1.3778947
A10: 5 | B10: GENT S4 addressable sounders | C10: ='Bid Tab'!C10 -> 60 | E10: =IF('Bid Tab'!E10="","",IFERROR('Bid Tab'!E10/'Bid Tab'!$C$10,"")) -> 95000 | F10: =IF('Bid Tab'!F10="","",IFERROR('Bid Tab'!F10/'Bid Tab'!$C$10,"")) -> 119900 | G10: =IF('Bid Tab'!G10="","",IFERROR('Bid Tab'!G10/'Bid Tab'!$C$10,"")) -> 90000 | H10: =IF('Bid Tab'!H10="","",IFERROR('Bid Tab'!H10/'Bid Tab'!$C$10,"")) -> 145000 | I10: =IF('Bid Tab'!I10="","",IFERROR('Bid Tab'!I10/'Bid Tab'!$C$10,"")) -> 27087.141 | J10: =MEDIAN(E10:H10) -> 107450 | K10: =IFERROR(MAX(E10:H10)/MIN(E10:H10),"") -> 1.6111111
A11: 6 | B11: GENT two-channel interface modules | C11: ='Bid Tab'!C11 -> 20 | E11: =IF('Bid Tab'!E11="","",IFERROR('Bid Tab'!E11/'Bid Tab'!$C$11,"")) -> 400000 | F11: =IF('Bid Tab'!F11="","",IFERROR('Bid Tab'!F11/'Bid Tab'!$C$11,"")) -> 134500 | G11: =IF('Bid Tab'!G11="","",IFERROR('Bid Tab'!G11/'Bid Tab'!$C$11,"")) -> 300000 | H11: =IF('Bid Tab'!H11="","",IFERROR('Bid Tab'!H11/'Bid Tab'!$C$11,"")) -> 165000 | I11: =IF('Bid Tab'!I11="","",IFERROR('Bid Tab'!I11/'Bid Tab'!$C$11,"")) -> 45136.05 | J11: =MEDIAN(E11:H11) -> 232500 | K11: =IFERROR(MAX(E11:H11)/MIN(E11:H11),"") -> 2.9739777
A12: 7 | B12: 1.5mm2 two-core flexible copper shielded fire-resistant cable, incl. termination and testing | C12: ='Bid Tab'!C12 -> 30 | E12: =IF('Bid Tab'!E12="","",IFERROR('Bid Tab'!E12/'Bid Tab'!$C$12,"")) -> 210000 | F12: =IF('Bid Tab'!F12="","",IFERROR('Bid Tab'!F12/'Bid Tab'!$C$12,"")) -> 148000 | G12: =IF('Bid Tab'!G12="","",IFERROR('Bid Tab'!G12/'Bid Tab'!$C$12,"")) -> 150000 | H12: =IF('Bid Tab'!H12="","",IFERROR('Bid Tab'!H12/'Bid Tab'!$C$12,"")) -> 205000 | I12: =IF('Bid Tab'!I12="","",IFERROR('Bid Tab'!I12/'Bid Tab'!$C$12,"")) -> 220000 | J12: =MEDIAN(E12:H12) -> 177500 | K12: =IFERROR(MAX(E12:H12)/MIN(E12:H12),"") -> 1.4189189
A13: 8 | B13: Piping, trunking, containment systems, supports and accessories for cable routing | C13: ='Bid Tab'!C13 -> 1 | E13: =IF('Bid Tab'!E13="","",IFERROR('Bid Tab'!E13/'Bid Tab'!$C$13,"")) -> 1000000 | F13: =IF('Bid Tab'!F13="","",IFERROR('Bid Tab'!F13/'Bid Tab'!$C$13,"")) -> 5150000 | G13: =IF('Bid Tab'!G13="","",IFERROR('Bid Tab'!G13/'Bid Tab'!$C$13,"")) -> 600000 | H13: =IF('Bid Tab'!H13="","",IFERROR('Bid Tab'!H13/'Bid Tab'!$C$13,"")) -> 500000 | I13: =IF('Bid Tab'!I13="","",IFERROR('Bid Tab'!I13/'Bid Tab'!$C$13,"")) -> 1000000 | J13: =MEDIAN(E13:H13) -> 800000 | K13: =IFERROR(MAX(E13:H13)/MIN(E13:H13),"") -> 10.3
A14: 9 | B14: GENT Plus addressable loop cards | C14: ='Bid Tab'!C14 -> 4 | E14: =IF('Bid Tab'!E14="","",IFERROR('Bid Tab'!E14/'Bid Tab'!$C$14,"")) -> 375000 | F14: =IF('Bid Tab'!F14="","",IFERROR('Bid Tab'!F14/'Bid Tab'!$C$14,"")) -> 450000 | G14: =IF('Bid Tab'!G14="","",IFERROR('Bid Tab'!G14/'Bid Tab'!$C$14,"")) -> 450000 | H14: =IF('Bid Tab'!H14="","",IFERROR('Bid Tab'!H14/'Bid Tab'!$C$14,"")) -> 385000 | I14: =IF('Bid Tab'!I14="","",IFERROR('Bid Tab'!I14/'Bid Tab'!$C$14,"")) -> 75274.973 | J14: =MEDIAN(E14:H14) -> 417500 | K14: =IFERROR(MAX(E14:H14)/MIN(E14:H14),"") -> 1.2 | L14: TotaGO's printed rate is 300,000; the derived rate is 375,000 because the line total is over-stated.
A15: 10 | B15: GENT 1-2 loop fire alarm panel (system expansion / integration) | C15: ='Bid Tab'!C15 -> 1 | E15: =IF('Bid Tab'!E15="","",IFERROR('Bid Tab'!E15/'Bid Tab'!$C$15,"")) -> 3000000 | F15: =IF('Bid Tab'!F15="","",IFERROR('Bid Tab'!F15/'Bid Tab'!$C$15,"")) -> 3450000 | G15: =IF('Bid Tab'!G15="","",IFERROR('Bid Tab'!G15/'Bid Tab'!$C$15,"")) -> 3500000 | H15: =IF('Bid Tab'!H15="","",IFERROR('Bid Tab'!H15/'Bid Tab'!$C$15,"")) | I15: =IF('Bid Tab'!I15="","",IFERROR('Bid Tab'!I15/'Bid Tab'!$C$15,"")) -> 879271.19 | J15: =MEDIAN(E15:H15) -> 3450000 | K15: =IFERROR(MAX(E15:H15)/MIN(E15:H15),"") -> 1.1666667
A16: 11 | B16: GENT network card for inter-panel communication and networking | C16: ='Bid Tab'!C16 -> 1 | E16: =IF('Bid Tab'!E16="","",IFERROR('Bid Tab'!E16/'Bid Tab'!$C$16,"")) -> 800000 | F16: =IF('Bid Tab'!F16="","",IFERROR('Bid Tab'!F16/'Bid Tab'!$C$16,"")) -> 620000 | G16: =IF('Bid Tab'!G16="","",IFERROR('Bid Tab'!G16/'Bid Tab'!$C$16,"")) -> 1000000 | H16: =IF('Bid Tab'!H16="","",IFERROR('Bid Tab'!H16/'Bid Tab'!$C$16,"")) -> 110000 | I16: =IF('Bid Tab'!I16="","",IFERROR('Bid Tab'!I16/'Bid Tab'!$C$16,"")) -> 104683.67 | J16: =MEDIAN(E16:H16) -> 710000 | K16: =IFERROR(MAX(E16:H16)/MIN(E16:H16),"") -> 9.0909091
A17: 12 | B17: Associated civil works, builders' works, installation materials and ancillary accessories | C17: ='Bid Tab'!C17 -> 1 | E17: =IF('Bid Tab'!E17="","",IFERROR('Bid Tab'!E17/'Bid Tab'!$C$17,"")) -> 3500000 | F17: =IF('Bid Tab'!F17="","",IFERROR('Bid Tab'!F17/'Bid Tab'!$C$17,"")) -> 5300000 | G17: =IF('Bid Tab'!G17="","",IFERROR('Bid Tab'!G17/'Bid Tab'!$C$17,"")) -> 4000000 | H17: =IF('Bid Tab'!H17="","",IFERROR('Bid Tab'!H17/'Bid Tab'!$C$17,"")) -> 500000 | I17: =IF('Bid Tab'!I17="","",IFERROR('Bid Tab'!I17/'Bid Tab'!$C$17,"")) -> 1000000 | J17: =MEDIAN(E17:H17) -> 3750000 | K17: =IFERROR(MAX(E17:H17)/MIN(E17:H17),"") -> 10.6
A18: 13 | B18: Professional services: design review, programming, testing, commissioning, as-built documentation, training, labour, handover | C18: ='Bid Tab'!C18 -> 1 | E18: =IF('Bid Tab'!E18="","",IFERROR('Bid Tab'!E18/'Bid Tab'!$C$18,"")) -> 15000000 | F18: =IF('Bid Tab'!F18="","",IFERROR('Bid Tab'!F18/'Bid Tab'!$C$18,"")) -> 4200000 | G18: =IF('Bid Tab'!G18="","",IFERROR('Bid Tab'!G18/'Bid Tab'!$C$18,"")) -> 12500000 | H18: =IF('Bid Tab'!H18="","",IFERROR('Bid Tab'!H18/'Bid Tab'!$C$18,"")) -> 7000000 | I18: =IF('Bid Tab'!I18="","",IFERROR('Bid Tab'!I18/'Bid Tab'!$C$18,"")) -> 8577100 | J18: =MEDIAN(E18:H18) -> 9750000 | K18: =IFERROR(MAX(E18:H18)/MIN(E18:H18),"") -> 3.5714286 | L18: Professional services / labour range 4.2m to 15.0m - the single largest driver of the spread between the GENT bids.

Sheet Normalisation
A1: NORMALISATION BRIDGE - AS QUOTED TO LIKE-FOR-LIKE
A2: Two classes of adjustment only: (a) arithmetic errors on the face of a bid, (b) RFP scope a bidder failed to price, imputed at the median of the bids that did price it.
A3: Yellow cells are imputed values, not bidder figures. No adjustment is made for scope a bidder ADDED - see 'Bid Tab' for those.
A5: Step | B5: Adjustment | C5: TotaGO | D5: Emo-Technical | E5: Potreal (PISL) | F5: JML / Fadayomi | G5: Roundbox | H5: Basis
A6: A | B6: Subtotal ex VAT, as quoted | C6: ='Bid Tab'!E20 -> 86825000 | D6: ='Bid Tab'!F20 -> 78201500 | E6: ='Bid Tab'!G20 -> 73490000 | F6: ='Bid Tab'!H20 -> 68050000 | G6: ='Bid Tab'!I20 -> 34167433 | H6: Face of each bidder's quotation.
A7: B | B7: Arithmetic correction | C7: -300000 | D7: 0 | E7: 0 | F7: 0 | G7: 0 | H7: TotaGO item 9: 4 loop cards @ 300,000 = 1,200,000, but the line total reads 1,500,000 and the printed subtotal only balances with the wrong figure.
A8: C | B8: Imputed: unpriced RFP scope | C8: 0 | D8: 0 | E8: 0 | F8: =MEDIAN('Bid Tab'!E15,'Bid Tab'!F15,'Bid Tab'!G15) -> 3450000 | G8: ='Bid Tab'!I14*3 -> 903299.67 | H8: JML: GENT 1-2 loop expansion panel not quoted - imputed at the median of the three GENT bids that priced it. Roundbox: supplies 1 of the 4 required loop cards - 3 added at its own rate.
A9: D | B9: ADJUSTED SUBTOTAL (ex VAT) | C9: =SUM(C6:C8) -> 86525000 | D9: =SUM(D6:D8) -> 78201500 | E9: =SUM(E6:E8) -> 73490000 | F9: =SUM(F6:F8) -> 71500000 | G9: =SUM(G6:G8) -> 35070733 | H9: A + B + C.
A10: E | B10: VAT @ 7.5% | C10: =C9*'Bid Tab'!$E$21 -> 6489375 | D10: =D9*'Bid Tab'!$E$21 -> 5865112.5 | E10: =E9*'Bid Tab'!$E$21 -> 5511750 | F10: =F9*'Bid Tab'!$E$21 -> 5362500 | G10: =G9*'Bid Tab'!$E$21 -> 2630305 | H10: Rate held on 'Bid Tab'.
A11: F | B11: ADJUSTED TOTAL (like-for-like, incl. VAT) | C11: =C9+C10 -> 93014375 | D11: =D9+D10 -> 84066612 | E11: =E9+E10 -> 79001750 | F11: =F9+F10 -> 76862500 | G11: =G9+G10 -> 37701038 | H11: D + E.
B13: Movement vs total as quoted | C13: =C11-'Bid Tab'!E23 -> -322500 | D13: =D11-'Bid Tab'!F23 -> 0 | E13: =E11-'Bid Tab'!G23 -> 0 | F13: =F11-'Bid Tab'!H23 -> 3708750 | G13: =G11-'Bid Tab'!I23 -> 971047.15 | H13: Negative = the bid overstated itself; positive = the bid was cheap because it left scope out.
B14: Adjusted total as % of lowest COMPLIANT bid | C14: =C11/MIN($C$11:$F$11)-1 -> 0.21013986 | D14: =D11/MIN($C$11:$F$11)-1 -> 0.093727273 | E14: =E11/MIN($C$11:$F$11)-1 -> 0.027832168 | F14: =F11/MIN($C$11:$F$11)-1 -> 0 | G14: =G11/MIN($C$11:$F$11)-1 -> -0.50950024 | H14: Compliant = GENT equipment as the RFP requires, so Roundbox (column G) is excluded from the benchmark.

Sheet Compliance
A1: COMPLIANCE & COMMERCIAL SUBMISSION MATRIX
A2: Tested against the RFP's stated contractor responsibilities and its required commercial submission.
A4: Evaluation reference date | B4: 46234 | C4: <- key input: validity is tested against this date
A6: Requirement | B6: TotaGO | C6: Emo-Technical | D6: Potreal (PISL) | E6: JML / Fadayomi | F6: Roundbox | G6: Comment
A7: Equipment offered is GENT, compatible with the existing Vigilon system | B7: Yes | C7: Yes | D7: Yes | E7: Yes | F7: NO | G7: The RFP requires genuine equipment compatible with the existing GENT Vigilon system. Roundbox substitutes TANDA throughout - a replacement system, not the upgrade that was tendered.
A8: All 13 BoQ lines priced | B8: Yes | C8: Yes | D8: Yes | E8: NO | F8: Partial | G8: JML omits the GENT 1-2 loop expansion panel. Roundbox supplies 1 loop card against the 4 required.
A9: Bid arithmetic reconciles | B9: NO | C9: Yes | D9: Yes | E9: Yes | F9: Yes | G9: TotaGO's loop-card line is over-stated by 300,000 and its subtotal only foots with the error. Rates on items 4 and 10 are also mistyped ("3,430,000,00", "3,000,00.00").
A10: VAT correctly stated | B10: Yes | C10: Yes | D10: Yes | E10: Yes | F10: NO | G10: Roundbox labels VAT "@ 5%" but the amount is exactly 7.5% of its subtotal. Amount right, label wrong - fix before it reaches a contract document.
A11: Delivery period stated | B11: No | C11: Yes | D11: No | E11: No | F11: No | G11: RFP requires it. Emo: 90 days.
A12: Project execution timeline stated | B12: No | C12: Yes | D12: No | E12: No | F12: Yes | G12: Emo: 60-90 days. Roundbox: 3 months.
A13: Warranty period stated in the bid | B13: No | C13: Yes | D13: No | E13: No | F13: Yes | G13: Emo: 12 months. Roundbox: 3 years on material. PISL states 6 months in its company profile but not in the quotation itself.
A14: Payment terms stated | B14: No | C14: Yes | D14: No | E14: No | F14: Yes | G14: Emo: 40% on LPO / 30% on delivery / 30% on completion. Roundbox: 100% material, 50% installation, balance before commissioning - heavily front-loaded and the weakest of the two for the client.
A15: Validity period stated | B15: Yes | C15: Yes | D15: Yes | E15: Yes | F15: Yes | G15: See dates below.
A17: Validity check
A18: Quote date | B18: 46101 | C18: 46220 | D18: 46195 | E18: 46196 | F18: 46234
A19: Validity stated (days) | B19: 7 | C19: 21 | D19: 30 | E19: 30 | F19: 14 | G19: PISL states "one month" and JML "30 days" - both taken as 30.
A20: Expires | B20: =B18+B19 -> 46108 | C20: =C18+C19 -> 46241 | D20: =D18+D19 -> 46225 | E20: =E18+E19 -> 46226 | F20: =F18+F19 -> 46248
A21: Still valid at reference date? | B21: =IF(B20>=$B$4,"Valid","EXPIRED") -> EXPIRED | C21: =IF(C20>=$B$4,"Valid","EXPIRED") -> Valid | D21: =IF(D20>=$B$4,"Valid","EXPIRED") -> EXPIRED | E21: =IF(E20>=$B$4,"Valid","EXPIRED") -> EXPIRED | F21: =IF(F20>=$B$4,"Valid","EXPIRED") -> Valid | G21: Three of the five bids have lapsed and would need to be re-confirmed in writing before any award.
A23: Document hygiene / integrity flags
A24: Emo-Technical | B24: Letterhead reads "LOCATION: NEW DRY POWDER MILK FACTORY" - copied from an unrelated quotation. Pricing itself is internally consistent.
A25: TotaGO | B25: Validity of 7 days from 20 March 2026; multiple numeric typos; subtotal depends on an over-stated line.
A26: Potreal (PISL) | B26: The archive is named after PISL's own proposal title and bundles PISL's 30-page company profile with the tender pack - note the possible conflict of interest in who assembled this bid set.
A27: JML / Fadayomi | B27: Vendor name does not appear in the document's text layer (logo only); signed "SeyiFadayomi", customer ref JMLINVICM. Confirm the legal entity before evaluating.
A28: Roundbox | B28: Quotes two panels against the single main-panel line; adds a handheld programmer not in the BoQ.

Sheet Notes & Sources
A1: NOTES, ASSUMPTIONS & SOURCES
A2: Every number in this workbook is either transcribed from one of the source PDFs, or derived by formula from those transcriptions. The only exceptions are the two imputed values listed below.
A4: # | B4: Topic | C4: Note
A5: 1 | B5: Source pack | C5: Seven PDFs supplied in PROPOSED_OVERHAUL_OF_THE_MALL_FIRE_DETECTION_AND_ALARM_SYSTEM1.zip: one client RFP, five vendor quotations, and one bidder company profile (ICM PROFILE.pdf, Potreal Insight Solutions Ltd).
A6: 2 | B6: Client requirement | C6: Source: REQUEST FOR PROPOSAL FOR THE REPAIR, REPLEMENT AND UPGRADING OF FIRE DETECTION AND ALARM SYSTEM..pdf - repair, replacement, upgrade, testing and recommissioning of the mall's addressable GENT Vigilon fire detection and alarm system.
A7: 3 | B7: Quantities | C7: The 13 BoQ quantities are the client's, taken from the RFP. The RFP also requires each bidder to verify quantities by site survey before execution, so they are not yet contractually fixed.
A8: 4 | B8: Line totals | C8: Transcribed as printed on each quotation (blue cells). Where a bidder split an RFP line across several of its own lines, the components are summed and the split is recorded in the 'Notes / exceptions' column of 'Bid Tab'.
A9: 5 | B9: VAT | C9: All five bids compute VAT at 7.5%, the Nigerian standard rate, and each printed total reproduces exactly on that basis. Roundbox's label reads "@ 5%" but its arithmetic is 7.5%.
A10: 6 | B10: IMPUTED VALUE 1 | C10: JML / Fadayomi did not price the GENT 1-2 loop expansion panel. Imputed at the median of the three GENT bids that did price it (3,000,000 / 3,450,000 / 3,500,000). This is an analyst estimate, not a bidder figure - shown in a yellow cell on 'Normalisation'.
A11: 7 | B11: IMPUTED VALUE 2 | C11: Roundbox supplies 1 loop card against the 4 required. Three additional cards imputed at Roundbox's own quoted rate. Analyst estimate - yellow cell on 'Normalisation'.
A12: 8 | B12: Deliberately NOT adjusted | C12: Scope a bidder ADDED beyond the RFP (Roundbox's second panel and its handheld programmer) stays inside the as-quoted subtotal, because it forms part of the subtotal that bidder printed. It is shown on its own row of 'Bid Tab' so it can be seen and stripped, but it is not deducted: whether the scope is wanted is the client's call, and guessing would move the totals on the analyst's judgement rather than on evidence.
A13: 9 | B13: Reconciliation | C13: 'Bid Tab' carries a check row proving this tabulation foots exactly to the subtotal printed on each of the five quotations - the difference row reads zero across all five columns.
A14: 10 | B14: Roundbox comparability | C14: Roundbox's total is roughly half the GENT bids because it substitutes TANDA equipment throughout - e.g. a smoke detector at ~20,600 delivered against 57,000-76,000 for GENT. The RFP requires equipment compatible with the existing GENT Vigilon system, so this is a rip-and-replace alternative, not a cheaper version of the tendered work. It is excluded from the compliant-bid ranking.
A15: 11 | B15: Heat detector variant | C15: The RFP asks for 60 "GENT S4 VAD Addressable Heat Detectors". Gent does build heat sensors with an integrated visual alarm device (S4-720-V-VAD-HPR red / -HPW white), so the wording is valid. The concern is pricing: at 57,000-76,000 per unit these lines sit below the plain sounder-VAD lines (90,000-145,000), which suggests bidders priced ordinary heat sensors rather than the VAD variant. Worth 60 units of clarification before award.
A16: 12 | B16: Part numbers verified | C16: Every Gent part number appearing in the bids is a real, current product: Vigilon Plus 24 panel, S4-715 optical smoke, S4-710 optical/heat multi-sensor, S4-720 heat, S4-700 common base, S4-34842 manual call point (EN54-11, with cover), and S3-S-VAD-HPR-R sounder/VAD from the S-Cubed range (EN54-23, Vigilon compatible). No bidder invented a part.
... A21: 17 | B21: What this workbook is not | C21: A technical evaluation. It compares price, scope coverage and commercial compliance only. No assessment has been made of any bidder's competence, references, or the condition of the existing installation.
A23: Legend
B24: Blue text - figure transcribed from a bidder's document
B25: Black text - calculated by formula
B26: Yellow fill - key input or analyst-imputed value; change these to re-run the comparison
B27: Orange fill - non-compliance or exception flag
